README
setup.py
pydawkiny/__init__.py
pydawkiny.egg-info/PKG-INFO
pydawkiny.egg-info/SOURCES.txt
pydawkiny.egg-info/dependency_links.txt
pydawkiny.egg-info/not-zip-safe
pydawkiny.egg-info/requires.txt
pydawkiny.egg-info/top_level.txt
pydawkiny/database/GetQuery.py
pydawkiny/database/ImportQuery.py
pydawkiny/database/__init__.py
pydawkiny/manufacture/Lot.py
pydawkiny/manufacture/__init__.py
pydawkiny/math/Geometry.py
pydawkiny/math/__init__.py
pydawkiny/sample/__init__.py
pydawkiny/sample/sample.py
pydawkiny/sample/datasets/__init__.py
pydawkiny/sample/datasets/dataManager.py
pydawkiny/sample/datasets/adult/__init__.py
pydawkiny/sample/datasets/wine/__init__.py
pydawkiny/statsmod/Geometry.py
pydawkiny/statsmod/HypoTests.py
pydawkiny/statsmod/__init__.py
pydawkiny/statsmod/feature_test.py
pydawkiny/tests/__init__.py
pydawkiny/tests/test.py
pydawkiny/tools/__init__.py
pydawkiny/tools/printwrappers.py