Metadata-Version: 1.1
Name: pydawkiny
Version: 0.1.3.6.38
Summary: Useful tools for Analysis
Home-page: http://github.com/dawkiny
Author: Young-Ju Kim
Author-email: dawkiny@gmail.com
License: MIT License
Platform: UNKNOWN
Classifier: Development Status :: 3 - Alpha
Classifier: Programming Language :: Python :: 3.5
